valimail/MailModule.py
valimail/__init__.py
valimail/file.py
valimail-0.1.4.dist-info/LICENSE
valimail-0.1.4.dist-info/METADATA
valimail-0.1.4.dist-info/WHEEL
valimail-0.1.4.dist-info/top_level.txt
valimail-0.1.4.dist-info/RECORD
