Metadata-Version: 2.1
Name: valimail
Version: 0.1.4
Summary: A library for advanced email verification.
Home-page: https://github.com/Poordotcom/Vali_Mail
Author: Adel Faisal
Author-email: Tomclans002@email.com
Classifier: Development Status :: 3 - Alpha
Classifier: Intended Audience :: Developers
Classifier: License :: OSI Approved :: MIT License
Classifier: Programming Language :: Python :: 3
Classifier: Programming Language :: Python :: 3.6
Classifier: Programming Language :: Python :: 3.7
Classifier: Programming Language :: Python :: 3.8
Classifier: Programming Language :: Python :: 3.9
Classifier: Programming Language :: Python :: 3.10
License-File: LICENSE
Requires-Dist: requests
Requires-Dist: disposable-email-domains
Requires-Dist: beautifulsoup4
Requires-Dist: python-whois
Requires-Dist: sockets
